LICENSE
README.md
setup.py
models_manager/__init__.py
models_manager/connect.py
models_manager/constants.py
models_manager/settings.py
models_manager/utils.py
models_manager.egg-info/PKG-INFO
models_manager.egg-info/SOURCES.txt
models_manager.egg-info/dependency_links.txt
models_manager.egg-info/requires.txt
models_manager.egg-info/top_level.txt
models_manager/converters/__init__.py
models_manager/converters/constructor.py
models_manager/converters/converters.py
models_manager/json/__init__.py
models_manager/json/provider.py
models_manager/manager/__init__.py
models_manager/manager/exeptions.py
models_manager/manager/model.py
models_manager/manager/query_set.py
models_manager/manager/field/__init__.py
models_manager/manager/field/enums.py
models_manager/manager/field/field.py
models_manager/manager/field/typing.py
models_manager/manager/managers/__init__.py
models_manager/manager/managers/base.py
models_manager/manager/managers/database.py
models_manager/manager/managers/json.py
models_manager/manager/managers/mixin.py
models_manager/manager/managers/schema.py
models_manager/manager/query/__init__.py
models_manager/manager/query/builder.py
models_manager/manager/query/node.py
models_manager/manager/query/operators.py
models_manager/negative/__init__.py
models_manager/negative/provider.py
models_manager/negative/validator.py
models_manager/providers/__init__.py
models_manager/providers/provider.py
models_manager/schema/__init__.py
models_manager/schema/context.py
models_manager/schema/provider.py
models_manager/schema/schema_template.py
models_manager/schema/schema_typing.py
models_manager/schema/validator.py