Metadata-Version: 2.1
Name: models-manager
Version: 1.0.1
Summary: Models Manager
Home-page: https://github.com/Nikita-Filonov/models_manager
Author: Nikita Filonov
Author-email: filonov.nikitkaa@gmail.com
License: UNKNOWN
Platform: UNKNOWN
License-File: LICENSE
